sshoot/__init__.py
sshoot/__main__.py
sshoot/autocomplete.py
sshoot/config.py
sshoot/i18n.py
sshoot/listing.py
sshoot/main.py
sshoot/manager.py
sshoot/profile.py
sshoot/locale/sshoot.pot
sshoot/locale/it_IT/LC_MESSAGES/sshoot.mo
sshoot/locale/it_IT/LC_MESSAGES/sshoot.po
sshoot-1.6.0.dist-info/LICENSE.txt
sshoot-1.6.0.dist-info/METADATA
sshoot-1.6.0.dist-info/WHEEL
sshoot-1.6.0.dist-info/entry_points.txt
sshoot-1.6.0.dist-info/top_level.txt
sshoot-1.6.0.dist-info/RECORD
