Metadata-Version: 2.1
Name: sshoot
Version: 1.6.0
Summary: Manage multiple sshuttle VPN sessions
Author-email: Alberto Donato <alberto.donato@gmail.com>
Maintainer-email: Alberto Donato <alberto.donato@gmail.com>
License: GNU GENERAL PUBLIC LICENSE
Project-URL: changelog, https://github.com/albertodonato/sshoot/blob/main/CHANGES.rst
Project-URL: homepage, https://github.com/albertodonato/sshoot
Keywords: ssh,sshuttle,vpn
Classifier: Development Status :: 5 - Production/Stable
Classifier: Environment :: Console
Classifier: Intended Audience :: Developers
Classifier: Intended Audience :: System Administrators
Classifier: License :: OSI Approved :: GNU General Public License v3 or later (GPLv3+)
Classifier: Operating System :: OS Independent
Classifier: Programming Language :: Python
Classifier: Programming Language :: Python :: 3 :: Only
Classifier: Programming Language :: Python :: 3.8
Classifier: Programming Language :: Python :: 3.9
Classifier: Programming Language :: Python :: 3.10
Classifier: Programming Language :: Python :: 3.11
Classifier: Topic :: System :: Networking
Classifier: Topic :: Utilities
Requires-Python: >=3.8
License-File: LICENSE.txt
Requires-Dist: argcomplete
Requires-Dist: prettytable
Requires-Dist: pyxdg
Requires-Dist: PyYAML
Requires-Dist: toolrack (>=3)
Provides-Extra: testing
Requires-Dist: pytest ; extra == 'testing'
Requires-Dist: pytest-mock ; extra == 'testing'
